billing/__init__.py
billing/admin.py
billing/apps.py
billing/billing_settings.py
billing/data/__init__.py
billing/data/default_usage_plans.py
billing/decorators.py
billing/management/__init__.py
billing/management/commands/__init__.py
billing/management/commands/stripe.py
billing/middleware.py
billing/migrations/0001_initial.py
billing/migrations/0002_initial.py
billing/migrations/__init__.py
billing/models.py
billing/service/__init__.py
billing/service/checkout_completed.py
billing/service/entitlements.py
billing/service/get_user.py
billing/service/plan_change.py
billing/service/price.py
billing/service/stripe_customer.py
billing/service/subscription_ended.py
billing/service/subscription_handler.py
billing/service/test.py
billing/signals/__init__.py
billing/signals/migrations.py
billing/signals/quotas.py
billing/signals/stripe/__init__.py
billing/signals/stripe/webhook_handler.py
billing/signals/usage.py
billing/templates/pages/billing/dashboard/all_subscriptions.html
billing/templates/pages/billing/dashboard/choose_plan_section.html
billing/templates/pages/billing/dashboard/dashboard.html
billing/templates/pages/billing/dashboard/growth_usages.html
billing/templates/pages/billing/dashboard/starter_usages.html
billing/urls.py
billing/views/__init__.py
billing/views/change_plan.py
billing/views/dashboard.py
billing/views/return_urls/failed.py
billing/views/return_urls/success.py
billing/views/stripe_misc.py
billing/views/stripe_webhooks.py
billing/views.py
core/__init__.py
core/admin.py
core/api/__init__.py
core/api/base/__init__.py
core/api/base/breadcrumbs.py
core/api/base/notifications.py
core/api/base/urls.py
core/api/emails/__init__.py
core/api/emails/fetch.py
core/api/emails/status.py
core/api/emails/urls.py
core/api/healthcheck/__init__.py
core/api/healthcheck/healthcheck.py
core/api/healthcheck/urls.py
core/api/landing_page/__init__.py
core/api/landing_page/email_waitlist.py
core/api/landing_page/urls.py
core/api/maintenance/__init__.py
strelix_core-0.0.8.dist-info/LICENSE
strelix_core-0.0.8.dist-info/METADATA
strelix_core-0.0.8.dist-info/WHEEL
strelix_core-0.0.8.dist-info/RECORD
