Metadata-Version: 2.1
Name: Strelix-Core
Version: 0.0.8
Summary: github.com/Strelix/core
Author: TreyWW
Requires-Python: >=3.10,<4.0
Classifier: Programming Language :: Python :: 3
Classifier: Programming Language :: Python :: 3.10
Classifier: Programming Language :: Python :: 3.11
Classifier: Programming Language :: Python :: 3.12
Classifier: Programming Language :: Python :: 3.13
Requires-Dist: bleach (==6.1.0)
Requires-Dist: boto3 (==1.34.76)
Requires-Dist: coverage (>=7.4.4,<8.0.0)
Requires-Dist: django (>=5.0.7,<6.0.0)
Requires-Dist: django-environ (==0.11.2)
Requires-Dist: django-htmx (==1.17.3)
Requires-Dist: django-login-required-middleware (==0.9.0)
Requires-Dist: django-ratelimit (==4.1.0)
Requires-Dist: django-silk (>=5.3.2,<6.0.0)
Requires-Dist: django-storages (==1.14.2)
Requires-Dist: djangorestframework (>=3.14.0,<4.0.0)
Requires-Dist: drf-yasg (>=1.21.7,<2.0.0)
Requires-Dist: mkdocs (>=1.5.3,<2.0.0)
Requires-Dist: mkdocs-git-committers-plugin-2 (>=2.3.0,<3.0.0)
Requires-Dist: mkdocs-material (>=9.5.15,<10.0.0)
Requires-Dist: pillow (==10.3.0)
Requires-Dist: setuptools (>=70.1.1,<71.0.0)
Requires-Dist: social-auth-app-django (>=5.4.2,<6.0.0)
Requires-Dist: stripe (>=10.8.0,<11.0.0)
Requires-Dist: tblib (>=3.0.0,<4.0.0)
Requires-Dist: typos (>=1.20.3,<2.0.0)
